dotrun.py
dotrun-2.6.1.dist-info/METADATA
dotrun-2.6.1.dist-info/WHEEL
dotrun-2.6.1.dist-info/entry_points.txt
dotrun-2.6.1.dist-info/RECORD
