Metadata-Version: 2.3
Name: dotrun
Version: 2.6.1
Summary: A tool for developing Node.js and Python projects
License: LGPL-3.0
Author: Canonical Web Team
Author-email: webteam@canonical.com
Requires-Python: >=3.10,<4.0
Classifier: License :: OSI Approved :: GNU Lesser General Public License v3 (LGPLv3)
Classifier: Programming Language :: Python :: 3
Classifier: Programming Language :: Python :: 3.10
Classifier: Programming Language :: Python :: 3.11
Classifier: Programming Language :: Python :: 3.12
Classifier: Programming Language :: Python :: 3.13
Requires-Dist: docker (==7.1.0)
Requires-Dist: dockerpty (==0.4.1)
Requires-Dist: python-dotenv (==1.0.1)
Requires-Dist: python-slugify (==8.0.4)
